ospy/__init__.py
ospy-0.0.2.data/scripts/ospy
ospy-0.0.2.dist-info/METADATA
ospy-0.0.2.dist-info/WHEEL
ospy-0.0.2.dist-info/top_level.txt
ospy-0.0.2.dist-info/RECORD
